Metadata-Version: 2.1
Name: nq
Version: 4.0.1
Summary: Nested Queries
Home-page: https://sgithub.fr.world.socgen/ktollec111518/nq
Author: SG
Author-email: 
License: UNKNOWN
Project-URL: Bug Reports, https://sgithub.fr.world.socgen/ktollec111518/nq/issues
Project-URL: Source, https://sgithub.fr.world.socgen/ktollec111518/nq
Keywords: dictionary nested query
Platform: UNKNOWN
Classifier: Development Status :: 3 - Alpha
Classifier: Intended Audience :: Developers
Classifier: Topic :: Software Development :: Libraries
Classifier: License :: OSI Approved :: MIT License
Classifier: Programming Language :: Python :: 3.6
Classifier: Programming Language :: Python :: 3.7
Provides-Extra: tests
